SapGuiLibrary/SapGuiLibrary.py
SapGuiLibrary/__init__.py
robotframework_sapguilibrary-1.1.dist-info/LICENSE
robotframework_sapguilibrary-1.1.dist-info/METADATA
robotframework_sapguilibrary-1.1.dist-info/WHEEL
robotframework_sapguilibrary-1.1.dist-info/top_level.txt
robotframework_sapguilibrary-1.1.dist-info/RECORD
