Metadata-Version: 2.1
Name: robotframework-sapguilibrary
Version: 1.1
Summary: A Robot Framework Library for automating the SAP GUI desktop client
Home-page: https://github.com/frankvanderkuur/robotframework-sapguilibrary
Author: Frank van der Kuur
Author-email: frank.vanderkuur@closesure.nl
License: UNKNOWN
Platform: UNKNOWN
Classifier: Programming Language :: Python :: 2.7
Classifier: Programming Language :: Python :: 3.6
Classifier: Operating System :: Microsoft :: Windows
Requires-Dist: pywin32 (>=222)
Requires-Dist: robotframework (>=2.9)
